daemonless_queuing/__init__.py
daemonless_queuing/lock.py
daemonless_queuing/py.typed
daemonless_queuing/queuing.py
daemonless_queuing/types.py
daemonless_queuing-0.0.6.dist-info/LICENSE
daemonless_queuing-0.0.6.dist-info/METADATA
daemonless_queuing-0.0.6.dist-info/WHEEL
daemonless_queuing-0.0.6.dist-info/top_level.txt
daemonless_queuing-0.0.6.dist-info/RECORD
